{"cameraMode":{"drawMode":0,"name":"Shaded","section":"Shading Mode"},"sceneLighting":true,"audioPlay":false,"sceneViewState":{"m_AlwaysRefresh":false,"showFog":true,"showSkybox":true,"showFlares":true,"showImageEffects":true,"showParticleSystems":true,"showVisualEffectGraphs":true,"m_FxEnabled":true},"in2DMode":false,"pivot":{"x":7.299060821533203,"y":6.059727191925049,"z":6.248989582061768},"rotation":{"x":0.1441338211297989,"y":-0.8542094230651856,"z":0.38085052371025088,"w":0.3232795298099518},"size":4.626355171203613,"orthographic":false}